[
  {
    "adnumber": 1,
    "text": "Why did the checkers player refuse to play chess? Because they couldn't handle all the 'knight'-mares on that board!"
  },
  {
    "adnumber": 2,
    "text": "Why did the checkers player laugh at the chessboard?\nBecause they thought the knight was trying to spell 'LOL' with all the L moves!"
  },
    {
    "adnumber": 3,
    "text": "Why did the checkers player cross the street? To get away from the chess game on the other side!"
  },
  {
    "adnumber": 4,
    "text": "Why did the checkers player avoid the chess tournament? Because they didn't want to be surrounded by a bunch of squares!"
  },
  {
    "adnumber": 5,
    "text": "I can't believe they made a board game out of a movie."
  },
  {
    "adnumber": 6,
    "text": "Have you cringed yet?"
  }
]
